Rhino-stubs/__init__.pyi
Rhino-stubs/ApplicationSettings/__init__.pyi
Rhino-stubs/Collections/__init__.pyi
Rhino-stubs/Commands/__init__.pyi
Rhino-stubs/Display/__init__.pyi
Rhino-stubs/DocObjects/__init__.pyi
Rhino-stubs/DocObjects/Custom/__init__.pyi
Rhino-stubs/DocObjects/SnapShots/__init__.pyi
Rhino-stubs/DocObjects/Tables/__init__.pyi
Rhino-stubs/FileIO/__init__.pyi
Rhino-stubs/Geometry/__init__.pyi
Rhino-stubs/Geometry/Collections/__init__.pyi
Rhino-stubs/Geometry/Intersect/__init__.pyi
Rhino-stubs/Geometry/MeshRefinements/__init__.pyi
Rhino-stubs/Geometry/Morphs/__init__.pyi
Rhino-stubs/Input/__init__.pyi
Rhino-stubs/Input/Custom/__init__.pyi
Rhino-stubs/NodeInCode/__init__.pyi
Rhino-stubs/PlugIns/__init__.pyi
Rhino-stubs/Render/__init__.pyi
Rhino-stubs/Render/ChangeQueue/__init__.pyi
Rhino-stubs/Render/DataSources/__init__.pyi
Rhino-stubs/Render/Fields/__init__.pyi
Rhino-stubs/Render/UI/__init__.pyi
Rhino-stubs/Runtime/__init__.pyi
Rhino-stubs/Runtime/InProcess/__init__.pyi
Rhino-stubs/Runtime/InteropWrappers/__init__.pyi
Rhino-stubs/Runtime/Notifications/__init__.pyi
Rhino-stubs/UI/__init__.pyi
Rhino-stubs/UI/Controls/__init__.pyi
Rhino-stubs/UI/Controls/DataSource/__init__.pyi
Rhino-stubs/UI/Controls/ThumbnailUI/__init__.pyi
Rhino-stubs/UI/Gumball/__init__.pyi
Rhino_stubs-0.0.1.dist-info/LICENSE
Rhino_stubs-0.0.1.dist-info/METADATA
Rhino_stubs-0.0.1.dist-info/WHEEL
Rhino_stubs-0.0.1.dist-info/top_level.txt
Rhino_stubs-0.0.1.dist-info/RECORD
