Metadata-Version: 2.1
Name: Rhino-stubs
Version: 0.0.1
Summary: Stubs for RhinoCommon
Home-page: UNKNOWN
Author: Robert McNeel & Associates
Author-email: steve@mcneel.com
License: UNKNOWN
Platform: UNKNOWN
Classifier: Development Status :: 3 - Alpha
Classifier: Intended Audience :: Developers
Classifier: License :: OSI Approved :: MIT License
Classifier: Programming Language :: Python
